blenderstudiomcp/__init__.py
blenderstudiomcp/server.py
blenderstudiomcp-0.1.0.dist-info/METADATA
blenderstudiomcp-0.1.0.dist-info/WHEEL
blenderstudiomcp-0.1.0.dist-info/entry_points.txt
blenderstudiomcp-0.1.0.dist-info/RECORD
