Metadata-Version: 2.4
Name: blenderstudiomcp
Version: 0.1.0
Summary: A MCP server for Blender
Author-email: cpjet64 <CURT.PETRICCA@YAHOO.COM>
Requires-Python: >=3.11
Requires-Dist: mcp>=1.4.1
